pymplschapters/__init__.py
pymplschapters/MPLS/__init__.py
pymplschapters/MPLS/load_AppInfoPlayList.py
pymplschapters/MPLS/load_ExtensionData.py
pymplschapters/MPLS/load_PlayItem.py
pymplschapters/MPLS/load_PlayList.py
pymplschapters/MPLS/load_PlayListMark.py
pymplschapters/MPLS/load_STNTable.py
pymplschapters/MPLS/load_StreamAttributes.py
pymplschapters/MPLS/load_StreamEntry.py
pymplschapters/MPLS/load_SubPath.py
pymplschapters/MPLS/load_SubPlayItem.py
pymplschapters/MPLS/load_header.py
pymplschapters-1.0.4.dist-info/LICENSE
pymplschapters-1.0.4.dist-info/METADATA
pymplschapters-1.0.4.dist-info/WHEEL
pymplschapters-1.0.4.dist-info/entry_points.txt
pymplschapters-1.0.4.dist-info/top_level.txt
pymplschapters-1.0.4.dist-info/RECORD
