Metadata-Version: 2.1
Name: pymplschapters
Version: 1.0.4
Summary: Extract chapters from a blu-ray mpls to a matroska recognized xml file
Home-page: https://github.com/rlaPHOENiX/pymplschapters
Author: PHOENiX
Author-email: rlaphoenix@pm.me
License: MIT
Platform: UNKNOWN
Classifier: License :: OSI Approved :: MIT License
Classifier: Operating System :: OS Independent
Requires-Dist: lxml (>=4.4.1)
